open_api_schemas_to_markdown/__init__.py
open_api_schemas_to_markdown/converter.py
open_api_schemas_to_markdown/translations.py
open_api_schemas_to_markdown-0.3.data/scripts/oa-to-md
open_api_schemas_to_markdown-0.3.dist-info/METADATA
open_api_schemas_to_markdown-0.3.dist-info/RECORD
open_api_schemas_to_markdown-0.3.dist-info/WHEEL
open_api_schemas_to_markdown-0.3.dist-info/top_level.txt
