Metadata-Version: 2.1
Name: open-api-schemas-to-markdown
Version: 0.3
Summary: Generate Markdown documentation from OpenAPI 3 Components Schemas
Home-page: https://github.com/entrepreneur-interet-general/open_api_schemas_to_markdown
Author: Antoine Augusti
Author-email: hi@antoine-augusti.fr
License: MIT
Keywords: openapi,documentation,markdown,gfm
Platform: UNKNOWN
Classifier: Development Status :: 3 - Alpha
Classifier: Intended Audience :: Developers
Classifier: License :: OSI Approved :: MIT License
Classifier: Programming Language :: Python :: 2.7
Classifier: Programming Language :: Python :: 3
Requires-Python: >=2.7, <4
Provides-Extra: dev
Requires-Dist: PyYAML
Requires-Dist: future
Requires-Dist: yamlordereddictloader
Provides-Extra: dev
Requires-Dist: nose; extra == 'dev'
